trailblazer/__about__.py
trailblazer/__init__.py
trailblazer/attack.py
trailblazer/cli.py
trailblazer/cloudtrail.py
trailblazer/enumerate.py
trailblazer/boto/__init__.py
trailblazer/boto/service.py
trailblazer/boto/sts.py
trailblazer/boto/util.py
trailblazer_aws-1.0.1.dist-info/DESCRIPTION.rst
trailblazer_aws-1.0.1.dist-info/METADATA
trailblazer_aws-1.0.1.dist-info/RECORD
trailblazer_aws-1.0.1.dist-info/WHEEL
trailblazer_aws-1.0.1.dist-info/entry_points.txt
trailblazer_aws-1.0.1.dist-info/metadata.json
trailblazer_aws-1.0.1.dist-info/top_level.txt
