Metadata-Version: 2.0
Name: trailblazer-aws
Version: 1.0.1
Summary: UNKNOWN
Home-page: UNKNOWN
Author: UNKNOWN
Author-email: UNKNOWN
License: UNKNOWN
Platform: UNKNOWN
Requires-Dist: boto3 (>=1.5.34)
Requires-Dist: click (==6.7)
Requires-Dist: click-log (==0.2.1)
Requires-Dist: PyYAML (==3.12)
